rl_with_panda_gym/__init__.py
rl_with_panda_gym/utils.py
rl_with_panda_gym/data/__init__.py
rl_with_panda_gym/data/make_dataset.py
rl_with_panda_gym/features/__init__.py
rl_with_panda_gym/features/build_features.py
rl_with_panda_gym/models/DDPG.py
rl_with_panda_gym/models/DQN.py
rl_with_panda_gym/models/REINFORCE.py
rl_with_panda_gym/models/__init__.py
rl_with_panda_gym/visualization/__init__.py
rl_with_panda_gym/visualization/visualize.py
rl_with_panda_gym/visualization/visualize_comparison.py
rl_with_panda_gym-0.1.1.dist-info/licenses/LICENSE
rl_with_panda_gym-0.1.1.dist-info/METADATA
rl_with_panda_gym-0.1.1.dist-info/WHEEL
rl_with_panda_gym-0.1.1.dist-info/top_level.txt
rl_with_panda_gym-0.1.1.dist-info/RECORD
