Metadata-Version: 2.4
Name: rl-with-panda-gym
Version: 0.1.1
Summary: Testing multiple RL algorithms on panda gym tasks
Author: Dasr Lab
Author-email: Davide Ermellino <ermellinodavide@gmail.com>
Requires-Python: ==3.11.*
License-File: LICENSE
Requires-Dist: tensorflow
Requires-Dist: panda-gym
Requires-Dist: gymnasium[classic-control]
Requires-Dist: numpy
Requires-Dist: matplotlib
Requires-Dist: tensorflow_probability
Requires-Dist: seaborn
Requires-Dist: tf_keras
Requires-Dist: h5py
Dynamic: author
Dynamic: license-file
